backoffice_extensions/__init__.py
backoffice_extensions/apps.py
backoffice_extensions/forms/__init__.py
backoffice_extensions/forms/widgets.py
backoffice_extensions/helpers.py
backoffice_extensions/locale/en/LC_MESSAGES/django.po
backoffice_extensions/locale/es/LC_MESSAGES/django.po
backoffice_extensions/mixins.py
backoffice_extensions/settings.py
backoffice_extensions/static/js/jquery.formset.js
backoffice_extensions/static/js/tailwind.js
backoffice_extensions/templates/backoffice/base.html
backoffice_extensions/templates/backoffice/bases/detail.html
backoffice_extensions/templates/backoffice/bases/form.html
backoffice_extensions/templates/backoffice/bases/list.html
backoffice_extensions/templates/backoffice/index.html
backoffice_extensions/templates/backoffice/layouts/default.html
backoffice_extensions/templates/backoffice/partials/delete_confirmation.html
backoffice_extensions/templates/backoffice/partials/filters.html
backoffice_extensions/templates/backoffice/partials/menu.html
backoffice_extensions/templates/backoffice/partials/pagination.html
backoffice_extensions/templates/backoffice/partials/search.html
backoffice_extensions/templates/backoffice/partials/statistics_values.html
backoffice_extensions/templates/backoffice/widgets/select.html
backoffice_extensions/templates/backoffice/widgets/select_multiple.html
backoffice_extensions/templatetags/__init__.py
backoffice_extensions/templatetags/backoffice.py
backoffice_extensions/views.py
django_backoffice_extensions-4.2.0.dist-info/AUTHORS.rst
django_backoffice_extensions-4.2.0.dist-info/LICENSE
django_backoffice_extensions-4.2.0.dist-info/METADATA
django_backoffice_extensions-4.2.0.dist-info/WHEEL
django_backoffice_extensions-4.2.0.dist-info/RECORD
